LICENSE
LICENSE.rst
MANIFEST.in
README.md
pyproject.toml
setup.cfg
setup.py
capsolver_python3/__init__.py
capsolver_python3/antiakamai_bmp.py
capsolver_python3/antikasada.py
capsolver_python3/capsolver.py
capsolver_python3/datadome_slider.py
capsolver_python3/fun_captcha.py
capsolver_python3/funcaptcha_classification.py
capsolver_python3/gee_test.py
capsolver_python3/h_captcha.py
capsolver_python3/hcaptcha_classification.py
capsolver_python3/image_to_text.py
capsolver_python3/proxy.py
capsolver_python3/recaptcha_v2.py
capsolver_python3/recaptcha_v2_enterprise.py
capsolver_python3/recaptcha_v3.py
capsolver_python3/request_type.py
capsolver_python3/useragent.py
capsolver_python3/utils.py
capsolver_python3.egg-info/PKG-INFO
capsolver_python3.egg-info/SOURCES.txt
capsolver_python3.egg-info/dependency_links.txt
capsolver_python3.egg-info/requires.txt
capsolver_python3.egg-info/top_level.txt