Metadata-Version: 2.1
Name: capsolver-python3
Version: 1.0.1
Summary: CapSolver.com library for Python3
Home-page: https://github.com/boredcoderx/capsolver_python3
Author: Boredcoder
License: MIT
Project-URL: Source, https://github.com/boredcoderx/capsolver_python3/
Project-URL: Tracker, https://github.com/boredcoderx/capsolver_python3/issues
Classifier: Development Status :: 4 - Beta
Classifier: License :: OSI Approved :: MIT License
Classifier: Programming Language :: Python :: 3
Classifier: Programming Language :: Python :: 3.6
Classifier: Programming Language :: Python :: 3.7
Classifier: Programming Language :: Python :: 3.8
Classifier: Programming Language :: Python :: 3.9
Requires: requests
Requires-Python: >=3
License-File: LICENSE
License-File: LICENSE.rst
